<?xml version="1.0" encoding="UTF-8"?>
<suite name="BANK GURU" parallel="tests" thread-count="3">
  
  <test name="Run on FIREFOX">
  	<parameter 	name = "browser" value = "firefox"></parameter>
    <classes>
      <class name="com.bankguru.account.Account_06_RegisterAndLogin_MultiBrowser_Parallel"/>
    </classes>
  </test>
  
  <test name="Run on CHROME">
  	<parameter 	name = "browser" value = "chrome"></parameter>
    <classes>
      <class name="com.bankguru.account.Account_06_RegisterAndLogin_MultiBrowser_Parallel"/>
    </classes>
  </test>
  
  <test name="Run on CHROMEHEADLESS">
  	<parameter 	name = "browser" value = "chromeheadless"></parameter>
    <classes>
      <class name="com.bankguru.account.Account_06_RegisterAndLogin_MultiBrowser_Parallel"/>
    </classes>
  </test>
  
  <test name="Run on IE">
  	<parameter 	name = "browser" value = "internetexplorer"></parameter>
    <classes>
      <class name="com.bankguru.account.Account_06_RegisterAndLogin_MultiBrowser_Parallel"/>
    </classes>
  </test> 
</suite> 
